[
    {
        "key": "dbln",
        "value": "%7B%2261560582695251%22%3A%22EFazYe21%22%2C%2261560804069152%22%3A%222RIPLU2U%22%7D",
        "domain": "facebook.com",
        "path": "/login/device-based/",
        "hostOnly": false,
        "creation": "2024-06-23T13:32:07.097Z",
        "lastAccessed": "2024-06-23T13:32:07.097Z"
    },
    {
        "key": "datr",
        "value": "0lFpZkiAMoOGVcHFKn4kUBKj",
        "domain": "facebook.com",
        "path": "/",
        "hostOnly": false,
        "creation": "2024-06-23T13:32:07.097Z",
        "lastAccessed": "2024-06-23T13:32:07.097Z"
    },
    {
        "key": "sb",
        "value": "0lFpZrxmBQywEm3ZUesGPKLH",
        "domain": "facebook.com",
        "path": "/",
        "hostOnly": false,
        "creation": "2024-06-23T13:32:07.097Z",
        "lastAccessed": "2024-06-23T13:32:07.097Z"
    },
    {
        "key": "vpd",
        "value": "v1%3B726x384x1.2372801303863525",
        "domain": "facebook.com",
        "path": "/",
        "hostOnly": false,
        "creation": "2024-06-23T13:32:07.097Z",
        "lastAccessed": "2024-06-23T13:32:07.097Z"
    },
    {
        "key": "ps_n",
        "value": "1",
        "domain": "facebook.com",
        "path": "/",
        "hostOnly": false,
        "creation": "2024-06-23T13:32:07.097Z",
        "lastAccessed": "2024-06-23T13:32:07.097Z"
    },
    {
        "key": "ps_l",
        "value": "1",
        "domain": "facebook.com",
        "path": "/",
        "hostOnly": false,
        "creation": "2024-06-23T13:32:07.097Z",
        "lastAccessed": "2024-06-23T13:32:07.097Z"
    },
    {
        "key": "dpr",
        "value": "1.2372801303863525",
        "domain": "facebook.com",
        "path": "/",
        "hostOnly": false,
        "creation": "2024-06-23T13:32:07.097Z",
        "lastAccessed": "2024-06-23T13:32:07.097Z"
    },
    {
        "key": "locale",
        "value": "en_US",
        "domain": "facebook.com",
        "path": "/",
        "hostOnly": false,
        "creation": "2024-06-23T13:32:07.097Z",
        "lastAccessed": "2024-06-23T13:32:07.097Z"
    },
    {
        "key": "wd",
        "value": "582x1101",
        "domain": "facebook.com",
        "path": "/",
        "hostOnly": false,
        "creation": "2024-06-23T13:32:07.097Z",
        "lastAccessed": "2024-06-23T13:32:07.097Z"
    },
    {
        "key": "fr",
        "value": "1mnaJg72UMFZrq8cO.AWWzaP7khiYtBmt6SiDxtOqlz5w.BmbuGA..AAA.0.0.BmeCN6.AWWWaFd4tKI",
        "domain": "facebook.com",
        "path": "/",
        "hostOnly": false,
        "creation": "2024-06-23T13:32:07.097Z",
        "lastAccessed": "2024-06-23T13:32:07.097Z"
    },
    {
        "key": "c_user",
        "value": "61560804069152",
        "domain": "facebook.com",
        "path": "/",
        "hostOnly": false,
        "creation": "2024-06-23T13:32:07.097Z",
        "lastAccessed": "2024-06-23T13:32:07.097Z"
    },
    {
        "key": "xs",
        "value": "37%3AutMGzT3wLQpqBg%3A2%3A1719149434%3A-1%3A-1",
        "domain": "facebook.com",
        "path": "/",
        "hostOnly": false,
        "creation": "2024-06-23T13:32:07.097Z",
        "lastAccessed": "2024-06-23T13:32:07.097Z"
    },
    {
        "key": "fbl_st",
        "value": "101239321%3BT%3A28652490",
        "domain": "facebook.com",
        "path": "/",
        "hostOnly": false,
        "creation": "2024-06-23T13:32:07.097Z",
        "lastAccessed": "2024-06-23T13:32:07.097Z"
    },
    {
        "key": "wl_cbv",
        "value": "v2%3Bclient_version%3A2537%3Btimestamp%3A1719149436",
        "domain": "facebook.com",
        "path": "/",
        "hostOnly": false,
        "creation": "2024-06-23T13:32:07.097Z",
        "lastAccessed": "2024-06-23T13:32:07.097Z"
    },
    {
        "key": "m_page_voice",
        "value": "61560804069152",
        "domain": "facebook.com",
        "path": "/",
        "hostOnly": false,
        "creation": "2024-06-23T13:32:07.097Z",
        "lastAccessed": "2024-06-23T13:32:07.097Z"
    }
]